ocsf/validate/compatibility/__init__.py
ocsf/validate/compatibility/__main__.py
ocsf/validate/compatibility/added_required_attrs.py
ocsf/validate/compatibility/changed_type.py
ocsf/validate/compatibility/example.toml
ocsf/validate/compatibility/increased_requirement.py
ocsf/validate/compatibility/py.typed
ocsf/validate/compatibility/removed_records.py
ocsf/validate/compatibility/removed_uids.py
ocsf/validate/compatibility/validator.py
ocsf_validate_compatibility-0.3.0.dist-info/LICENSE
ocsf_validate_compatibility-0.3.0.dist-info/METADATA
ocsf_validate_compatibility-0.3.0.dist-info/WHEEL
ocsf_validate_compatibility-0.3.0.dist-info/entry_points.txt
ocsf_validate_compatibility-0.3.0.dist-info/RECORD
