Metadata-Version: 2.1
Name: ocsf-validate-compatibility
Version: 0.3.0
Summary: Tools for working with the OCSF schema
License: Apache-2.0
Author: Jeremy Fisher
Author-email: jeremy@query.ai
Requires-Python: >=3.11,<4.0
Classifier: License :: OSI Approved :: Apache Software License
Classifier: Programming Language :: Python :: 3
Classifier: Programming Language :: Python :: 3.11
Requires-Dist: ocsf-lib (>=0.2.0,<0.3.0)
Requires-Dist: semver (>=3.0.2,<4.0.0)
Requires-Dist: termcolor (>=2.4.0,<3.0.0)
